citeproc_py_styles-0.1.4.dist-info/licenses/AUTHORS.rst
citeproc_py_styles-0.1.4.dist-info/licenses/LICENSE
citeproc_styles/__init__.py
citeproc_styles/errors.py
citeproc_styles/version.py
citeproc_py_styles-0.1.4.dist-info/METADATA
citeproc_py_styles-0.1.4.dist-info/WHEEL
citeproc_py_styles-0.1.4.dist-info/top_level.txt
citeproc_py_styles-0.1.4.dist-info/RECORD
