Metadata-Version: 2.4
Name: citeproc-py-styles
Version: 0.1.4
Summary: CSL styles.
Home-page: https://github.com/inveniosoftware/citeproc-py-styles
Author: CERN
Author-email: info@inveniosoftware.org
License: MIT
Keywords: citeproc styles csl
Platform: any
Classifier: Environment :: Web Environment
Classifier: Intended Audience :: Developers
Classifier: License :: OSI Approved :: MIT License
Classifier: Operating System :: OS Independent
Classifier: Programming Language :: Python
Classifier: Topic :: Software Development :: Libraries :: Python Modules
Classifier: Programming Language :: Python :: 3
Classifier: Programming Language :: Python :: 3.6
Classifier: Programming Language :: Python :: 3.7
Classifier: Development Status :: 5 - Production/Stable
License-File: LICENSE
License-File: AUTHORS.rst
Requires-Dist: lxml>=4.1.1
Requires-Dist: six>=1.10.0
Provides-Extra: tests
Requires-Dist: pytest-invenio>=1.4.0; extra == "tests"
Provides-Extra: all
Requires-Dist: pytest-invenio>=1.4.0; extra == "all"
Requires-Dist: pytest-invenio>=1.4.0; extra == "all"
Dynamic: author
Dynamic: author-email
Dynamic: classifier
Dynamic: description
Dynamic: home-page
Dynamic: keywords
Dynamic: license
Dynamic: license-file
Dynamic: platform
Dynamic: provides-extra
Dynamic: requires-dist
Dynamic: summary
